mlint/__init__.py
mlint/derived_variables.py
mlint/verification.py
mlint/visualisation.py
mlint/data_prep/__init__.py
mlint/data_prep/combine.py
mlint/data_prep/combine_nwp.py
mlint/data_prep/retrieve_data_cds.py
tests/__init__.py
tests/fixture_data.py
tests/fixtures.py
tests/generate_test_data.py
tests/test_derived_variables.py
mlint-0.1.0.dist-info/LICENSE
mlint-0.1.0.dist-info/METADATA
mlint-0.1.0.dist-info/WHEEL
mlint-0.1.0.dist-info/top_level.txt
mlint-0.1.0.dist-info/RECORD
