Metadata-Version: 2.2
Name: mlint
Version: 0.1.0
Summary: The ML Model Intercomparison package facilitates calculation of autmated verification statistics and other forms of evaluation on ML weather models.
Author-email: Met Office <stephen.haddad@metoffice.gov.uk>
Project-URL: Homepage, https://www.metoffice.gov.uk/
Project-URL: Repository, https://github.com/MetOffice/ml_model_intercomparison
Classifier: Programming Language :: Python :: 3
Classifier: License :: OSI Approved :: MIT License
Classifier: Operating System :: OS Independent
Requires-Python: >=3.8
License-File: LICENSE
Requires-Dist: ncdata==0.1.1
Requires-Dist: cdsapi==0.7.3
Requires-Dist: numpy>=2.1.3
Requires-Dist: MetPy>=1.6.3
Requires-Dist: scitools-iris==3.11.0
Requires-Dist: matplotlib
Requires-Dist: sphinx
Requires-Dist: setuptools
Requires-Dist: sphinx_rtd_theme
